{
  "db": "PostgreSQL",
  "02c53411d8986e5117c804ffee2a9ba7b6b3066ee8f7a501f774b7f5330a1f61": {
    "describe": {
      "columns": [
        {
          "name": "usd",
          "ordinal": 0,
          "type_info": "Float8"
        },
        {
          "name": "timestamp",
          "ordinal": 1,
          "type_info": "Timestamptz"
        }
      ],
      "nullable": [
        false,
        false
      ],
      "parameters": {
        "Left": [
          "Numeric"
        ]
      }
    },
    "query": "\n            WITH\n              eth_price_distances AS (\n                SELECT\n                  ethusd,\n                  timestamp,\n                  ABS(\n                    EXTRACT(\n                      epoch\n                      FROM\n                        (timestamp - (NOW() - '24 hours':: INTERVAL))\n                    )\n                  ) AS distance_seconds\n                FROM\n                  eth_prices\n                ORDER BY\n                  distance_seconds ASC\n              )\n            SELECT ethusd AS usd, timestamp\n            FROM eth_price_distances\n            WHERE distance_seconds <= $1\n            LIMIT 1\n            "
  },
  "05f76b83575171bc7275f2f3ff3100a9d6150192e67a29a3f1fa80cdead19f47": {
    "describe": {
      "columns": [],
      "nullable": [],
      "parameters": {
        "Left": [
          "Text",
          "Text",
          "Int8",
          "Int8",
          "Int8",
          "Int8",
          "Text",
          "Text"
        ]
      }
    },
    "query": "\n        INSERT INTO beacon_blocks (\n            block_hash,\n            block_root,\n            deposit_sum,\n            deposit_sum_aggregated,\n            withdrawal_sum,\n            withdrawal_sum_aggregated,\n            parent_root,\n            state_root\n        )\n        VALUES (\n            $1, $2, $3, $4, $5, $6, $7, $8\n        )\n        "
  },
  "0a008d415e6395b49f8168f50baeb5ccb61602fb739683a6ec0fbf98dbc3a490": {
    "describe": {
      "columns": [
        {
          "name": "block_root",
          "ordinal": 0,
          "type_info": "Text"
        },
        {
          "name": "slot!",
          "ordinal": 1,
          "type_info": "Int4"
        }
      ],
      "nullable": [
        false,
        false
      ],
      "parameters": {
        "Left": [
          "Int4"
        ]
      }
    },
    "query": "\n            SELECT\n                block_root,\n                slot AS \"slot!\"\n            FROM\n                beacon_blocks\n            JOIN beacon_states ON\n                beacon_blocks.state_root = beacon_states.state_root\n            WHERE\n                slot >= $1\n        "
  },
  "0a2508d2c3fbce38482cdb84e0e3bd6983a0a50d3e2036b9e8237a89d4ecdd14": {
    "describe": {
      "columns": [
        {
          "name": "supply!",
          "ordinal": 0,
          "type_info": "Text"
        }
      ],
      "nullable": [
        null
      ],
      "parameters": {
        "Left": []
      }
    },
    "query": "\n        SELECT\n            supply::TEXT AS \"supply!\"\n        FROM\n            eth_supply\n        ORDER BY\n            timestamp DESC\n        LIMIT 1\n        "
  },
  "0c32c06017ce791e3d195e4b3ef5e00ccae7a682e2efec6024e10b017dd3a97f": {
    "describe": {
      "columns": [
        {
          "name": "slot",
          "ordinal": 0,
          "type_info": "Int4"
        }
      ],
      "nullable": [
        false
      ],
      "parameters": {
        "Left": []
      }
    },
    "query": "\n        SELECT\n            beacon_states.slot\n        FROM\n            beacon_states\n        JOIN beacon_blocks ON\n            beacon_states.state_root = beacon_blocks.state_root\n        JOIN execution_supply ON\n            beacon_blocks.block_hash = execution_supply.block_hash\n        WHERE\n            execution_supply.block_hash IS NOT NULL\n        ORDER BY beacon_states.slot DESC\n        LIMIT 1\n        "
  },
  "100d831ec3a9d8ea9545ca0bcaae004558fc96771fe31a755ae04625d38b0000": {
    "describe": {
      "columns": [
        {
          "name": "pg_notify",
          "ordinal": 0,
          "type_info": "Void"
        }
      ],
      "nullable": [
        null
      ],
      "parameters": {
        "Left": [
          "Text"
        ]
      }
    },
    "query": "\n            SELECT pg_notify('cache-update', $1)\n        "
  },
  "145ea2e8e6ed4a9cc41990b66b1a72624b534772405dfa45d6adf212bd14aec7": {
    "describe": {
      "columns": [
        {
          "name": "effective_balance_sum",
          "ordinal": 0,
          "type_info": "Int8"
        }
      ],
      "nullable": [
        true
      ],
      "parameters": {
        "Left": [
          "Text"
        ]
      }
    },
    "query": "\n        SELECT\n            effective_balance_sum\n        FROM\n            beacon_states\n        WHERE\n            state_root = $1\n        "
  },
  "146416f8451be76f2f9f4f686f19babf08bdf86d7e4ce9c6e171df3ab5058ddb": {
    "describe": {
      "columns": [
        {
          "name": "max",
          "ordinal": 0,
          "type_info": "Int4"
        }
      ],
      "nullable": [
        null
      ],
      "parameters": {
        "Left": []
      }
    },
    "query": "\n            SELECT\n                MAX(block_number)\n            FROM\n                execution_supply_deltas\n        "
  },
  "14fe911032ff0992a50fde6b869cd3fd54e19f6e28cbcc21182a9bfa0869c52a": {
    "describe": {
      "columns": [],
      "nullable": [],
      "parameters": {
        "Left": [
          "Timestamptz",
          "Int4",
          "Int4",
          "Int4",
          "Numeric"
        ]
      }
    },
    "query": "\n        INSERT INTO eth_supply (\n            timestamp,\n            block_number,\n            deposits_slot,\n            balances_slot,\n            supply\n        )\n        VALUES ($1, $2, $3, $4, $5::NUMERIC)\n        "
  },
  "1b0b8bba7f8e9980b737ec1358fa83b27a96f77824d4617a2b60a0878eac7753": {
    "describe": {
      "columns": [
        {
          "name": "five_minute_timestamp!",
          "ordinal": 0,
          "type_info": "Timestamptz"
        },
        {
          "name": "supply!",
          "ordinal": 1,
          "type_info": "Float8"
        }
      ],
      "nullable": [
        null,
        null
      ],
      "parameters": {
        "Left": [
          "Interval"
        ]
      }
    },
    "query": "\n                SELECT\n                    DISTINCT ON (DATE_BIN('5 minutes', timestamp, '2022-01-01')) DATE_BIN('5 minutes', timestamp, '2022-01-01') AS \"five_minute_timestamp!\",\n                    supply::FLOAT8 / 1e18 AS \"supply!\"\n                FROM\n                    eth_supply\n                WHERE\n                    timestamp >= NOW() - $1::INTERVAL\n                ORDER BY\n                    DATE_BIN('5 minutes', timestamp, '2022-01-01'), timestamp ASC\n                "
  },
  "1d1cbed2bd2dfa388a1b9851e9c772e23c8256c278762aadda6413f26a06341e": {
    "describe": {
      "columns": [],
      "nullable": [],
      "parameters": {
        "Left": [
          "Int4"
        ]
      }
    },
    "query": "\n            DELETE FROM beacon_states\n            WHERE slot = $1\n        "
  },
  "1f30489a7d32047b3d46923f0e9ec3684b8e5079c1912eae85c7fefbd79d638b": {
    "describe": {
      "columns": [
        {
          "name": "epoch_timestamp!",
          "ordinal": 0,
          "type_info": "Timestamptz"
        },
        {
          "name": "supply!",
          "ordinal": 1,
          "type_info": "Float8"
        }
      ],
      "nullable": [
        null,
        null
      ],
      "parameters": {
        "Left": [
          "Interval"
        ]
      }
    },
    "query": "\n                SELECT\n                    DISTINCT ON (date_bin('384 seconds', timestamp, '2022-1-1')) date_bin('384 seconds', timestamp, '2022-1-1') AS \"epoch_timestamp!\",\n                    supply::FLOAT8 / 1e18 AS \"supply!\"\n                FROM\n                    eth_supply\n                WHERE\n                    timestamp >= NOW() - $1::INTERVAL\n                ORDER BY\n                    date_bin('384 seconds', timestamp, '2022-1-1'), timestamp ASC\n                "
  },
  "1fa92738082529c0bac77c40e91b937054b3f20bd17d5daa721943b5c4d08b5e": {
    "describe": {
      "columns": [],
      "nullable": [],
      "parameters": {
        "Left": [
          "Int4"
        ]
      }
    },
    "query": "\n        DELETE FROM beacon_validators_balance\n        WHERE state_root IN (\n            SELECT state_root FROM beacon_states\n            WHERE slot >= $1\n        )\n        "
  },
  "224362632b86d95f0e331e0391d148632baacc826c2ba532d7b55fc51c562fa2": {
    "describe": {
      "columns": [
        {
          "name": "hour_timestamp!",
          "ordinal": 0,
          "type_info": "Timestamptz"
        },
        {
          "name": "supply!",
          "ordinal": 1,
          "type_info": "Float8"
        }
      ],
      "nullable": [
        null,
        null
      ],
      "parameters": {
        "Left": [
          "Interval"
        ]
      }
    },
    "query": "\n                SELECT\n                    DISTINCT ON (DATE_TRUNC('hour', timestamp)) DATE_TRUNC('hour', timestamp) AS \"hour_timestamp!\",\n                    supply::FLOAT8 / 1e18 AS \"supply!\"\n                FROM\n                    eth_supply\n                WHERE\n                    timestamp >= NOW() - $1::INTERVAL\n                ORDER BY\n                    DATE_TRUNC('hour', timestamp), timestamp ASC\n                "
  },
  "2345c8d8037c9244b3ef6af000c37cfc47691d343becb49046c39bb0481d28e9": {
    "describe": {
      "columns": [
        {
          "name": "deposit_sum_aggregated",
          "ordinal": 0,
          "type_info": "Int8"
        }
      ],
      "nullable": [
        false
      ],
      "parameters": {
        "Left": [
          "Text"
        ]
      }
    },
    "query": "\n        SELECT\n            deposit_sum_aggregated\n        FROM\n            beacon_blocks\n        WHERE\n            block_root = $1\n        "
  },
  "26022725182b69f2b8a9695711836592df07efb3a1561c046294646ab178b5e7": {
    "describe": {
      "columns": [],
      "nullable": [],
      "parameters": {
        "Left": [
          "TextArray",
          "Int4Array",
          "Int4Array",
          "TextArray",
          "TimestamptzArray",
          "Float8Array",
          "NumericArray"
        ]
      }
    },
    "query": "\n            INSERT INTO burn_sums (\n                time_frame,\n                first_included_block_number,\n                last_included_block_number,\n                last_included_block_hash,\n                timestamp,\n                sum_usd,\n                sum_wei\n            )\n            SELECT * FROM UNNEST (\n                $1::text[],\n                $2::int[],\n                $3::int[],\n                $4::text[],\n                $5::timestamptz[],\n                $6::float8[],\n                $7::numeric[]\n            )\n            "
  },
  "28409ca2bee68e0969632f7278e521cae6fb20ec9247d24680b29ac9b727aaa2": {
    "describe": {
      "columns": [
        {
          "name": "slot",
          "ordinal": 0,
          "type_info": "Int4"
        }
      ],
      "nullable": [
        false
      ],
      "parameters": {
        "Left": []
      }
    },
    "query": "\n                SELECT slot FROM beacon_states\n                ORDER BY slot ASC\n            "
  },
  "290d9e93fbfdf99bba0541e4bfcef8b938a0b9a7717c4a08185717b716e47f88": {
    "describe": {
      "columns": [
        {
          "name": "number",
          "ordinal": 0,
          "type_info": "Int4"
        },
        {
          "name": "base_fee_per_gas!",
          "ordinal": 1,
          "type_info": "Int8"
        }
      ],
      "nullable": [
        false,
        false
      ],
      "parameters": {
        "Left": []
      }
    },
    "query": "\n            SELECT\n                number,\n                base_fee_per_gas AS \"base_fee_per_gas!\"\n            FROM\n                blocks_next\n            ORDER BY base_fee_per_gas ASC\n            LIMIT 1\n            "
  },
  "2953654cbf712f2a858ed77d3cb5c4b8110fa09720510ee46758971a36b4a980": {
    "describe": {
      "columns": [
        {
          "name": "number",
          "ordinal": 0,
          "type_info": "Int4"
        }
      ],
      "nullable": [
        false
      ],
      "parameters": {
        "Left": [
          "Timestamptz"
        ]
      }
    },
    "query": "\n            SELECT\n                number\n            FROM\n                blocks_next\n            WHERE\n                timestamp >= $1\n            ORDER BY\n                timestamp ASC\n            LIMIT 1\n            "
  },
  "2f09abb216302c7104189e963ee218ac6fa64fe9c07a13633830397efb726258": {
    "describe": {
      "columns": [],
      "nullable": [],
      "parameters": {
        "Left": [
          "Int4"
        ]
      }
    },
    "query": "\n            DELETE FROM burn_sums\n            WHERE last_included_block_number < $1\n            "
  },
  "31185ac31b749332808469a232a9c7e5a12964142a1328f0a7d26d9fb2ad0bb1": {
    "describe": {
      "columns": [
        {
          "name": "day_timestamp!",
          "ordinal": 0,
          "type_info": "Timestamptz"
        },
        {
          "name": "supply!",
          "ordinal": 1,
          "type_info": "Float8"
        }
      ],
      "nullable": [
        null,
        null
      ],
      "parameters": {
        "Left": []
      }
    },
    "query": "\n                -- We select only one row per day, using ORDER BY to make sure it's the first.\n                -- The column we output is rounded to whole days for convenience.\n                SELECT\n                    DISTINCT ON (DATE_TRUNC('day', timestamp)) DATE_TRUNC('day', timestamp) AS \"day_timestamp!\",\n                    supply::FLOAT8 / 1e18 AS \"supply!\"\n                FROM\n                    eth_supply\n                ORDER BY\n                    DATE_TRUNC('day', timestamp), timestamp ASC\n                "
  },
  "33d31f5bc0c8dde9581f22d69b2fb82986e574cb7272a8dda02fb3543e133647": {
    "describe": {
      "columns": [],
      "nullable": [],
      "parameters": {
        "Left": [
          "Int4"
        ]
      }
    },
    "query": "\n        DELETE FROM beacon_issuance\n        WHERE state_root IN (\n            SELECT state_root FROM beacon_states\n            WHERE slot = $1\n        )\n        "
  },
  "376e760f404471d87aac22f443ea64ace718725a92af4474a7c8391ad17d4baa": {
    "describe": {
      "columns": [],
      "nullable": [],
      "parameters": {
        "Left": [
          "Int4"
        ]
      }
    },
    "query": "\n        DELETE FROM\n            eth_supply\n        WHERE\n            deposits_slot >= $1\n            OR balances_slot >= $1\n        "
  },
  "38ec7400dc9786404908540972937958a5a62e686512e0607550a9434ec2995f": {
    "describe": {
      "columns": [
        {
          "name": "number",
          "ordinal": 0,
          "type_info": "Int4"
        },
        {
          "name": "base_fee_per_gas!",
          "ordinal": 1,
          "type_info": "Int8"
        }
      ],
      "nullable": [
        false,
        false
      ],
      "parameters": {
        "Left": [
          "Interval"
        ]
      }
    },
    "query": "\n            SELECT\n                number,\n                base_fee_per_gas AS \"base_fee_per_gas!\"\n            FROM\n                blocks_next\n            WHERE\n                timestamp >= NOW() - $1::INTERVAL\n            ORDER BY base_fee_per_gas ASC\n            LIMIT 1\n            "
  },
  "39782012967f4e32a1cda1a226ed802dffebfb8b111ae3a12d1f3469608da4b7": {
    "describe": {
      "columns": [],
      "nullable": [],
      "parameters": {
        "Left": [
          "Timestamptz",
          "Text",
          "Int8"
        ]
      }
    },
    "query": "\n        INSERT INTO beacon_validators_balance (timestamp, state_root, gwei) VALUES ($1, $2, $3)\n        "
  },
  "39c4e81b03c50cf4e0b568dde7feab19e44cd115b44c9a298f3fc02cbfb1d292": {
    "describe": {
      "columns": [
        {
          "name": "number",
          "ordinal": 0,
          "type_info": "Int4"
        },
        {
          "name": "base_fee_per_gas!",
          "ordinal": 1,
          "type_info": "Int8"
        }
      ],
      "nullable": [
        false,
        false
      ],
      "parameters": {
        "Left": []
      }
    },
    "query": "\n            SELECT\n                number,\n                base_fee_per_gas AS \"base_fee_per_gas!\"\n            FROM\n                blocks_next\n            WHERE\n                timestamp >= '2022-09-15T06:42:42Z'::TIMESTAMPTZ\n            ORDER BY base_fee_per_gas ASC\n            LIMIT 1\n            "
  },
  "3aed21a5e1ed297fedd5953b77216cbd3554f52859a5d4bf435b132c91ad89ed": {
    "describe": {
      "columns": [
        {
          "name": "balances_slot",
          "ordinal": 0,
          "type_info": "Int4"
        }
      ],
      "nullable": [
        false
      ],
      "parameters": {
        "Left": [
          "Int4"
        ]
      }
    },
    "query": "\n        SELECT\n            balances_slot\n        FROM\n            eth_supply\n        WHERE\n            balances_slot = $1\n        "
  },
  "3beca1df64753ceeade24fca690ef352165b33b851c3f8db40cefb7738e2b1f4": {
    "describe": {
      "columns": [
        {
          "name": "timestamp",
          "ordinal": 0,
          "type_info": "Timestamptz"
        },
        {
          "name": "supply",
          "ordinal": 1,
          "type_info": "Float8"
        }
      ],
      "nullable": [
        false,
        false
      ],
      "parameters": {
        "Left": [
          "Timestamptz",
          "Timestamptz"
        ]
      }
    },
    "query": "\n        SELECT\n            timestamp,\n            supply\n        FROM daily_supply_glassnode\n        WHERE timestamp >= $1\n        AND timestamp < $2\n        ORDER BY timestamp ASC\n        "
  },
  "3d2eeee2f4479ee8f9cc9095b81a9e9d9415c301f2645283bd689df2839351f1": {
    "describe": {
      "columns": [
        {
          "name": "timestamp",
          "ordinal": 0,
          "type_info": "Timestamptz"
        },
        {
          "name": "ethusd!",
          "ordinal": 1,
          "type_info": "Float8"
        }
      ],
      "nullable": [
        false,
        false
      ],
      "parameters": {
        "Left": [
          "Timestamptz"
        ]
      }
    },
    "query": "\n        SELECT\n          timestamp,\n          ethusd AS \"ethusd!\"\n        FROM eth_prices\n        ORDER BY ABS(EXTRACT(epoch FROM (timestamp - $1)))\n        LIMIT 1\n        "
  },
  "3e71ae5b218c205c14cad0ce43a9e5fc08eb0c7d0c5d0bd9fe1629d67f83dfe9": {
    "describe": {
      "columns": [
        {
          "name": "number",
          "ordinal": 0,
          "type_info": "Int4"
        },
        {
          "name": "base_fee_per_gas!",
          "ordinal": 1,
          "type_info": "Int8"
        }
      ],
      "nullable": [
        false,
        false
      ],
      "parameters": {
        "Left": [
          "Timestamptz"
        ]
      }
    },
    "query": "\n            SELECT\n                number,\n                base_fee_per_gas AS \"base_fee_per_gas!\"\n            FROM\n                blocks_next\n            WHERE\n                timestamp >= $1\n            ORDER BY base_fee_per_gas DESC\n            LIMIT 1\n            "
  },
  "49360b2160a50eaf2d3e27daa2fc138d995b6a42ff3a2de4d3f59b727d36e985": {
    "describe": {
      "columns": [
        {
          "name": "timestamp",
          "ordinal": 0,
          "type_info": "Timestamptz"
        },
        {
          "name": "supply",
          "ordinal": 1,
          "type_info": "Float8"
        }
      ],
      "nullable": [
        false,
        false
      ],
      "parameters": {
        "Left": [
          "Timestamptz",
          "Timestamptz"
        ]
      }
    },
    "query": "\n        SELECT\n            timestamp,\n            supply\n        FROM daily_supply_glassnode\n        WHERE timestamp < $1\n        AND timestamp >= $2\n        ORDER BY timestamp ASC\n        "
  },
  "4af8583a1cc8a87929d6625b1a3019920c56b8c7c0b3a6b0708763ed3d386ed3": {
    "describe": {
      "columns": [
        {
          "name": "withdrawal_sum_aggregated",
          "ordinal": 0,
          "type_info": "Int8"
        }
      ],
      "nullable": [
        true
      ],
      "parameters": {
        "Left": [
          "Text"
        ]
      }
    },
    "query": "\n        SELECT\n            withdrawal_sum_aggregated\n        FROM\n            beacon_blocks\n        WHERE\n            block_root = $1\n        "
  },
  "4c311cd6fc10898b9a865fe7f2b50dec072356e8d0f9dc0b6185423a035769fb": {
    "describe": {
      "columns": [
        {
          "name": "block_root",
          "ordinal": 0,
          "type_info": "Text"
        },
        {
          "name": "state_root",
          "ordinal": 1,
          "type_info": "Text"
        },
        {
          "name": "parent_root",
          "ordinal": 2,
          "type_info": "Text"
        },
        {
          "name": "deposit_sum",
          "ordinal": 3,
          "type_info": "Int8"
        },
        {
          "name": "deposit_sum_aggregated",
          "ordinal": 4,
          "type_info": "Int8"
        },
        {
          "name": "block_hash",
          "ordinal": 5,
          "type_info": "Text"
        }
      ],
      "nullable": [
        false,
        false,
        false,
        false,
        false,
        true
      ],
      "parameters": {
        "Left": [
          "Int4"
        ]
      }
    },
    "query": "\n        SELECT\n            block_root,\n            beacon_blocks.state_root,\n            parent_root,\n            deposit_sum,\n            deposit_sum_aggregated,\n            block_hash\n        FROM\n            beacon_blocks\n        JOIN beacon_states ON\n            beacon_blocks.state_root = beacon_states.state_root\n        WHERE\n            slot = $1\n        "
  },
  "4e14d0c252de8aa55a6b99a9c432c75982cf7ec4783339d19473729ccc310a02": {
    "describe": {
      "columns": [
        {
          "name": "timestamp",
          "ordinal": 0,
          "type_info": "Timestamptz"
        },
        {
          "name": "supply",
          "ordinal": 1,
          "type_info": "Float8"
        }
      ],
      "nullable": [
        false,
        false
      ],
      "parameters": {
        "Left": [
          "Timestamptz"
        ]
      }
    },
    "query": "\n        SELECT\n            timestamp,\n            supply\n        FROM daily_supply_glassnode\n        WHERE timestamp < $1\n        ORDER BY timestamp ASC\n        "
  },
  "4f33c5d4b851b645f1e49b3666841146232c99799e9390421814229745c5e110": {
    "describe": {
      "columns": [
        {
          "name": "state_root",
          "ordinal": 0,
          "type_info": "Text"
        }
      ],
      "nullable": [
        false
      ],
      "parameters": {
        "Left": [
          "Int4"
        ]
      }
    },
    "query": "\n            SELECT\n                state_root\n            FROM\n                beacon_states\n            WHERE\n                slot = $1\n        "
  },
  "4faf5f18f446d8614f80c6771957263fa497640ca2f6332b25d02fec90b61fe2": {
    "describe": {
      "columns": [
        {
          "name": "count!",
          "ordinal": 0,
          "type_info": "Int8"
        }
      ],
      "nullable": [
        null
      ],
      "parameters": {
        "Left": [
          "Int4"
        ]
      }
    },
    "query": "\n        SELECT\n            COUNT(*) AS \"count!\"\n        FROM\n            beacon_states\n        LEFT JOIN beacon_validators_balance ON\n            beacon_states.state_root = beacon_validators_balance.state_root\n        WHERE\n            slot >= $1\n        AND\n            beacon_validators_balance.state_root IS NULL\n        "
  },
  "51ef5e66cebfc87b3dc99d2122dfb2c23dca5a446a4d0d560d947247a167968d": {
    "describe": {
      "columns": [
        {
          "name": "average!",
          "ordinal": 0,
          "type_info": "Float8"
        }
      ],
      "nullable": [
        null
      ],
      "parameters": {
        "Left": [
          "Int4"
        ]
      }
    },
    "query": "\n                    SELECT\n                        SUM(base_fee_per_gas::FLOAT8 * gas_used::FLOAT8) / SUM(gas_used::FLOAT8) AS \"average!\"\n                    FROM\n                        blocks_next\n                    WHERE\n                        number >= $1\n                    "
  },
  "525ee7f8caaabc8aeb791b8ccc613762405b9ef746d7b25dedada0240a67f9b5": {
    "describe": {
      "columns": [],
      "nullable": [],
      "parameters": {
        "Left": [
          "Text",
          "Int4"
        ]
      }
    },
    "query": "\n            INSERT INTO\n                beacon_states\n                (state_root, slot)\n            VALUES\n                ($1, $2)\n        "
  },
  "54b14a11d3f218965976264262ac71197336e770c4732d2cd361225e03772673": {
    "describe": {
      "columns": [],
      "nullable": [],
      "parameters": {
        "Left": [
          "Int4"
        ]
      }
    },
    "query": "\n        DELETE FROM beacon_validators_balance\n        WHERE state_root IN (\n            SELECT state_root FROM beacon_states\n            WHERE slot = $1\n        )\n        "
  },
  "5561d31bc1555e9049cfab19024d1e6f53a5a1de4686317066c1806cf9ea4e3b": {
    "describe": {
      "columns": [],
      "nullable": [],
      "parameters": {
        "Left": [
          "Int4"
        ]
      }
    },
    "query": "\n            DELETE FROM\n                burn_sums\n            WHERE\n                last_included_block_number >= $1\n            "
  },
  "55d22ce3778a0a15030cc6b5ae5fa2b4856e4f92e082c7cfc560a47aab34a6a8": {
    "describe": {
      "columns": [
        {
          "name": "block_root",
          "ordinal": 0,
          "type_info": "Text"
        },
        {
          "name": "state_root",
          "ordinal": 1,
          "type_info": "Text"
        },
        {
          "name": "parent_root",
          "ordinal": 2,
          "type_info": "Text"
        },
        {
          "name": "deposit_sum",
          "ordinal": 3,
          "type_info": "Int8"
        },
        {
          "name": "deposit_sum_aggregated",
          "ordinal": 4,
          "type_info": "Int8"
        },
        {
          "name": "block_hash",
          "ordinal": 5,
          "type_info": "Text"
        }
      ],
      "nullable": [
        false,
        false,
        false,
        false,
        false,
        true
      ],
      "parameters": {
        "Left": [
          "Int4"
        ]
      }
    },
    "query": "\n        SELECT\n            block_root,\n            beacon_blocks.state_root,\n            parent_root,\n            deposit_sum,\n            deposit_sum_aggregated,\n            block_hash\n        FROM\n            beacon_blocks \n        JOIN beacon_states ON\n            beacon_blocks.state_root = beacon_states.state_root \n        WHERE slot < $1\n        ORDER BY slot DESC \n        LIMIT 1\n        "
  },
  "57078faa5541b50ec9487ceda072ba2b46a55ebf9f66ffebecf38b2d4a1e4469": {
    "describe": {
      "columns": [
        {
          "name": "hash",
          "ordinal": 0,
          "type_info": "Text"
        }
      ],
      "nullable": [
        false
      ],
      "parameters": {
        "Left": [
          "Int4"
        ]
      }
    },
    "query": "\n            SELECT\n                hash\n            FROM\n                blocks_next\n            WHERE\n                number = $1\n            "
  },
  "58a9a8ae222d1c817a8dec63edbc27bab498e47427b2eaa147177fb7bcfeee62": {
    "describe": {
      "columns": [],
      "nullable": [],
      "parameters": {
        "Left": [
          "Int4"
        ]
      }
    },
    "query": "\n        DELETE FROM beacon_blocks\n        WHERE state_root IN (\n            SELECT\n                state_root\n            FROM\n                beacon_states\n            WHERE beacon_states.slot >= $1\n        )\n        "
  },
  "5c0ebd75feae47d74c50bc83c80a9f61c6d3a8304cfca8a04a4d0ad66340f863": {
    "describe": {
      "columns": [
        {
          "name": "max",
          "ordinal": 0,
          "type_info": "Int4"
        }
      ],
      "nullable": [
        null
      ],
      "parameters": {
        "Left": []
      }
    },
    "query": "\n        SELECT\n            MAX(balances_slot)\n        FROM\n            eth_supply\n        "
  },
  "635c841223a110075c5e88878f1d20c80532255799f6fe926259dbaa88fbf881": {
    "describe": {
      "columns": [
        {
          "name": "first_included_block_number",
          "ordinal": 0,
          "type_info": "Int4"
        },
        {
          "name": "last_included_block_number",
          "ordinal": 1,
          "type_info": "Int4"
        },
        {
          "name": "last_included_block_hash",
          "ordinal": 2,
          "type_info": "Text"
        },
        {
          "name": "timestamp",
          "ordinal": 3,
          "type_info": "Timestamptz"
        },
        {
          "name": "sum_usd",
          "ordinal": 4,
          "type_info": "Float8"
        },
        {
          "name": "sum_wei!",
          "ordinal": 5,
          "type_info": "Text"
        }
      ],
      "nullable": [
        false,
        false,
        false,
        false,
        false,
        null
      ],
      "parameters": {
        "Left": [
          "Text"
        ]
      }
    },
    "query": "\n            SELECT\n                first_included_block_number,\n                last_included_block_number,\n                last_included_block_hash,\n                timestamp,\n                sum_usd,\n                sum_wei::TEXT AS \"sum_wei!\"\n            FROM burn_sums\n            WHERE time_frame = $1\n            ORDER BY last_included_block_number DESC\n            LIMIT 1\n            "
  },
  "69e60d2bedbe66e19419b4bfa8c8ba5bf46e254feecbf00a0fd051dd291c6add": {
    "describe": {
      "columns": [
        {
          "name": "gwei",
          "ordinal": 0,
          "type_info": "Int8"
        }
      ],
      "nullable": [
        false
      ],
      "parameters": {
        "Left": [
          "Interval"
        ]
      }
    },
    "query": "\n        WITH issuance_distances AS (\n            SELECT\n              gwei,\n              timestamp,\n              ABS(\n                EXTRACT(\n                  epoch\n                  FROM\n                    (timestamp - (NOW() - $1::INTERVAL))\n                )\n              ) AS distance_seconds\n            FROM\n              beacon_issuance\n            ORDER BY\n              distance_seconds ASC\n            LIMIT 100\n        )\n        SELECT gwei\n        FROM issuance_distances \n        -- while we have holes in the data, we limit distance to 2 days\n        WHERE distance_seconds <= 172800\n        LIMIT 1\n        "
  },
  "70fe7aeee3f5bfadebafd85d7a6dd4afced8b08c7072baadef6d180af03813c4": {
    "describe": {
      "columns": [],
      "nullable": [],
      "parameters": {
        "Left": [
          "Text",
          "Text"
        ]
      }
    },
    "query": "\n        UPDATE\n            beacon_blocks\n        SET\n            block_hash = $1\n        WHERE\n            block_root = $2\n        "
  },
  "73d291d9db99ddd05727fadba267f267d5b1b4a06c4bb827f76c101b185b6e08": {
    "describe": {
      "columns": [
        {
          "name": "exists!",
          "ordinal": 0,
          "type_info": "Bool"
        }
      ],
      "nullable": [
        null
      ],
      "parameters": {
        "Left": [
          "Int4"
        ]
      }
    },
    "query": "\n            SELECT EXISTS (\n                SELECT 1\n                FROM execution_supply_deltas\n                WHERE block_number = $1\n            ) AS \"exists!\"\n        "
  },
  "74686dd09493c11746a41929cc7785f376f9039a5525a95be503d375801a15e4": {
    "describe": {
      "columns": [
        {
          "name": "avg!",
          "ordinal": 0,
          "type_info": "Float8"
        }
      ],
      "nullable": [
        null
      ],
      "parameters": {
        "Left": [
          "Timestamptz",
          "Timestamptz"
        ]
      }
    },
    "query": "\n            SELECT AVG(ethusd) AS \"avg!\"\n            FROM eth_prices\n            WHERE timestamp >= $1\n            AND timestamp <= $2\n            "
  },
  "7a0f47afbae84d65766452b366e2fa4567e97e125a4cce2707f0e1114ca5c6e2": {
    "describe": {
      "columns": [],
      "nullable": [],
      "parameters": {
        "Left": [
          "Timestamptz",
          "Float8"
        ]
      }
    },
    "query": "\n            INSERT INTO\n                eth_prices (timestamp, ethusd)\n            VALUES ($1, $2)\n            ON CONFLICT (timestamp) DO UPDATE SET\n                ethusd = excluded.ethusd\n            "
  },
  "7c862e1e38d41362c623695a6975a3068074fc4cb27c09aa4f077fde6ed91533": {
    "describe": {
      "columns": [
        {
          "name": "gwei",
          "ordinal": 0,
          "type_info": "Int8"
        }
      ],
      "nullable": [
        false
      ],
      "parameters": {
        "Left": [
          "Text"
        ]
      }
    },
    "query": "\n        SELECT\n            gwei\n        FROM\n            beacon_validators_balance\n        WHERE\n            beacon_validators_balance.state_root = $1\n        "
  },
  "7c8ce12377837516c1b52c711729f7ac5a07f0a924ff1227b5b7374de482ce7f": {
    "describe": {
      "columns": [],
      "nullable": [],
      "parameters": {
        "Left": [
          "Int4"
        ]
      }
    },
    "query": "\n        DELETE FROM blocks_next\n        WHERE number >= $1\n        "
  },
  "872177b7547af8196a990b8de0a381be7b0694656ead1748d0c8b0d0da2b2231": {
    "describe": {
      "columns": [
        {
          "name": "value",
          "ordinal": 0,
          "type_info": "Jsonb"
        }
      ],
      "nullable": [
        true
      ],
      "parameters": {
        "Left": [
          "Text"
        ]
      }
    },
    "query": "\n            SELECT value FROM key_value_store\n            WHERE key = $1\n        "
  },
  "88b950efda6150dc3a044420e67b11138cd14fbfca10c53a5b9f640bd5a45610": {
    "describe": {
      "columns": [],
      "nullable": [],
      "parameters": {
        "Left": [
          "Text",
          "Jsonb"
        ]
      }
    },
    "query": "\n            INSERT INTO key_value_store (key, value) VALUES ($1, $2)\n            ON CONFLICT (key) DO UPDATE SET\n                value = excluded.value\n        "
  },
  "8c73136998c1db86353e475ce346ec87d78a2daf0d9775e9c0f88b119c0fe632": {
    "describe": {
      "columns": [
        {
          "name": "count!",
          "ordinal": 0,
          "type_info": "Int8"
        }
      ],
      "nullable": [
        null
      ],
      "parameters": {
        "Left": [
          "Int4"
        ]
      }
    },
    "query": "\n            SELECT\n                COUNT(*) AS \"count!\"\n            FROM\n                beacon_blocks\n            JOIN beacon_states ON\n                beacon_blocks.state_root = beacon_states.state_root\n            WHERE\n                slot >= $1\n            AND\n                block_hash IS NULL\n        "
  },
  "8ecdb845a8d20242d267393d5c79173f8de281f872a806ec2dd85f49d1c675fc": {
    "describe": {
      "columns": [
        {
          "name": "slot",
          "ordinal": 0,
          "type_info": "Int4"
        },
        {
          "name": "state_root",
          "ordinal": 1,
          "type_info": "Text"
        }
      ],
      "nullable": [
        false,
        false
      ],
      "parameters": {
        "Left": [
          "Int4",
          "Int4"
        ]
      }
    },
    "query": "\n                SELECT\n                    slot,\n                    state_root\n                FROM\n                    beacon_states\n                WHERE\n                    slot >= $1\n                AND\n                    slot <= $2\n                ORDER BY\n                    slot ASC\n            "
  },
  "91013ee5f53e5dcaf39a4cff0df3f34c8e7709e334863c41a35a8a375e235804": {
    "describe": {
      "columns": [],
      "nullable": [],
      "parameters": {
        "Left": [
          "Int4",
          "Int4"
        ]
      }
    },
    "query": "\n            DELETE FROM\n                blocks_next\n            WHERE\n                number >= $1\n            AND\n                number <= $2\n            "
  },
  "91af0d1eb493c6c6f0516ff07c471382563b9aa342797b59a0708920d0575325": {
    "describe": {
      "columns": [
        {
          "name": "gwei",
          "ordinal": 0,
          "type_info": "Int8"
        }
      ],
      "nullable": [
        false
      ],
      "parameters": {
        "Left": []
      }
    },
    "query": "\n        SELECT\n            gwei\n        FROM\n            beacon_issuance\n        ORDER BY\n            timestamp DESC\n        LIMIT 1\n        "
  },
  "99161f8c9a73c0713c2fefb04cbc70c933371910f7956d459404391a11cb0eb6": {
    "describe": {
      "columns": [
        {
          "name": "tips_since_london!",
          "ordinal": 0,
          "type_info": "Float8"
        }
      ],
      "nullable": [
        null
      ],
      "parameters": {
        "Left": []
      }
    },
    "query": "\n            SELECT SUM(tips) / 1e9 AS \"tips_since_london!\" FROM blocks\n        "
  },
  "9cbd141c5fe47fb5806c00c1fb2e87c21ee0ba939097ffea77eac019c5be164a": {
    "describe": {
      "columns": [
        {
          "name": "timestamp",
          "ordinal": 0,
          "type_info": "Timestamptz"
        },
        {
          "name": "supply!",
          "ordinal": 1,
          "type_info": "Float8"
        }
      ],
      "nullable": [
        false,
        null
      ],
      "parameters": {
        "Left": [
          "Interval"
        ]
      }
    },
    "query": "\n                SELECT\n                    timestamp,\n                    supply::FLOAT8 / 1e18 AS \"supply!\"\n                FROM\n                    eth_supply\n                WHERE\n                    timestamp >= NOW() - $1::INTERVAL\n                ORDER BY\n                    timestamp ASC\n                "
  },
  "9fd4f5582d534d68ba6d1cd86abc49e1dad76f38ab45cd85c0ca9295a1629cc1": {
    "describe": {
      "columns": [],
      "nullable": [],
      "parameters": {
        "Left": [
          "Int8",
          "Text"
        ]
      }
    },
    "query": "\n        UPDATE\n            beacon_states\n        SET\n            effective_balance_sum = $1\n        WHERE\n            state_root = $2\n        "
  },
  "a071befc1dabc8df4310891a11943b3d9e337870cc85e36fe30151a3a02937c0": {
    "describe": {
      "columns": [
        {
          "name": "number",
          "ordinal": 0,
          "type_info": "Int4"
        }
      ],
      "nullable": [
        false
      ],
      "parameters": {
        "Left": []
      }
    },
    "query": "\n        SELECT\n            number\n        FROM\n            blocks_next\n        ORDER BY number DESC\n        LIMIT 1\n        "
  },
  "a3d5a3dc158b75b9ef06af433f5120fbdde7754553522ce31fa2fb18ce3e7234": {
    "describe": {
      "columns": [
        {
          "name": "timestamp",
          "ordinal": 0,
          "type_info": "Timestamptz"
        },
        {
          "name": "supply!",
          "ordinal": 1,
          "type_info": "Float8"
        }
      ],
      "nullable": [
        false,
        null
      ],
      "parameters": {
        "Left": []
      }
    },
    "query": "\n        SELECT\n            timestamp,\n            supply::FLOAT8 / 1e18 AS \"supply!\"\n        FROM\n            eth_supply\n        ORDER BY timestamp DESC\n        LIMIT 1\n        "
  },
  "a6b279224781f0cd9677718f9387480aaf0e98ee921a91ed63ef52eb6f6493b5": {
    "describe": {
      "columns": [
        {
          "name": "state_root",
          "ordinal": 0,
          "type_info": "Text"
        },
        {
          "name": "slot",
          "ordinal": 1,
          "type_info": "Int4"
        }
      ],
      "nullable": [
        false,
        false
      ],
      "parameters": {
        "Left": [
          "Int4"
        ]
      }
    },
    "query": "\n        SELECT\n            beacon_states.state_root,\n            beacon_states.slot\n        FROM\n            beacon_states\n        LEFT JOIN beacon_validators_balance ON\n            beacon_states.state_root = beacon_validators_balance.state_root\n        WHERE\n            slot >= $1\n        AND\n            beacon_validators_balance.state_root IS NULL\n        ORDER BY slot DESC\n        "
  },
  "abf3b6b71ceb87bf2f711262eb4ddd7e5bb839a465da07a902d5332f221f32d6": {
    "describe": {
      "columns": [
        {
          "name": "exists!",
          "ordinal": 0,
          "type_info": "Bool"
        }
      ],
      "nullable": [
        null
      ],
      "parameters": {
        "Left": [
          "Int4"
        ]
      }
    },
    "query": "\n            SELECT EXISTS (\n                SELECT 1\n                FROM blocks_next\n                WHERE number = $1\n            ) AS \"exists!\"\n            "
  },
  "afc80a58058ec48b784e3e6fabb6a2aaffac18fe875c12c880c73c86690fb4be": {
    "describe": {
      "columns": [
        {
          "name": "state_root",
          "ordinal": 0,
          "type_info": "Text"
        },
        {
          "name": "slot: Slot",
          "ordinal": 1,
          "type_info": "Int4"
        }
      ],
      "nullable": [
        false,
        false
      ],
      "parameters": {
        "Left": []
      }
    },
    "query": "\n            SELECT\n                beacon_states.state_root,\n                beacon_states.slot AS \"slot: Slot\"\n            FROM beacon_states\n            ORDER BY slot DESC\n            LIMIT 1\n        "
  },
  "b2688f2135e83c9a84ec1f3b1a866922a1663083c2b2e826de9d7232da47b9cd": {
    "describe": {
      "columns": [
        {
          "name": "timestamp",
          "ordinal": 0,
          "type_info": "Timestamptz"
        },
        {
          "name": "usd",
          "ordinal": 1,
          "type_info": "Float8"
        }
      ],
      "nullable": [
        false,
        false
      ],
      "parameters": {
        "Left": []
      }
    },
    "query": "\n            SELECT\n                timestamp, ethusd AS usd\n            FROM\n                eth_prices\n            ORDER BY timestamp DESC\n            LIMIT 1\n            "
  },
  "b74c08aa0d4962b217a17a9463115a9a125b1874146ea6ff2a32231ab186f489": {
    "describe": {
      "columns": [
        {
          "name": "day_timestamp!",
          "ordinal": 0,
          "type_info": "Timestamptz"
        },
        {
          "name": "base_fee_per_gas!",
          "ordinal": 1,
          "type_info": "Float8"
        }
      ],
      "nullable": [
        null,
        null
      ],
      "parameters": {
        "Left": [
          "Timestamptz"
        ]
      }
    },
    "query": "\n                SELECT\n                    DATE_TRUNC('day', timestamp) AS \"day_timestamp!\",\n                    SUM(base_fee_per_gas::float8 * gas_used::float8) / SUM(gas_used::float8) AS \"base_fee_per_gas!\"\n                FROM\n                    blocks_next\n                WHERE\n                    timestamp >= $1\n                GROUP BY \"day_timestamp!\"\n                ORDER BY \"day_timestamp!\" ASC\n                "
  },
  "b963875714b300b2b0cc7694f8e77ad6f77203de4ad1e6b394a7c64ac380ea5c": {
    "describe": {
      "columns": [
        {
          "name": "exists!",
          "ordinal": 0,
          "type_info": "Bool"
        }
      ],
      "nullable": [
        null
      ],
      "parameters": {
        "Left": [
          "Text"
        ]
      }
    },
    "query": "\n            SELECT EXISTS (\n                SELECT 1\n                FROM execution_supply_deltas\n                WHERE block_hash = $1\n            ) AS \"exists!\"\n        "
  },
  "bfc3d6da794a828526867dd2547eff7d22a929fa98544723e52c97c3ec53f92a": {
    "describe": {
      "columns": [],
      "nullable": [],
      "parameters": {
        "Left": [
          "Timestamptz",
          "Text",
          "Int8"
        ]
      }
    },
    "query": "INSERT INTO beacon_issuance (timestamp, state_root, gwei) VALUES ($1, $2, $3)"
  },
  "c32f56e69bb255a91820cc0bd0c28a1cecc3b95d01a300cc11fda80ead4cd677": {
    "describe": {
      "columns": [
        {
          "name": "day_timestamp!",
          "ordinal": 0,
          "type_info": "Timestamptz"
        },
        {
          "name": "gwei",
          "ordinal": 1,
          "type_info": "Int8"
        }
      ],
      "nullable": [
        null,
        false
      ],
      "parameters": {
        "Left": []
      }
    },
    "query": "\n        SELECT\n            DISTINCT ON (DATE_TRUNC('day', timestamp)) DATE_TRUNC('day', timestamp) AS \"day_timestamp!\",\n            gwei\n        FROM\n            beacon_validators_balance\n        ORDER BY\n            DATE_TRUNC('day', timestamp), timestamp ASC\n        "
  },
  "c4f33536e0cf242082981afb66afbea9ee8c06cd39c61fa2c617d0ed2fb03caf": {
    "describe": {
      "columns": [],
      "nullable": [],
      "parameters": {
        "Left": [
          "Int4"
        ]
      }
    },
    "query": "\n            DELETE FROM beacon_states\n            WHERE slot >= $1\n        "
  },
  "c74b396270ebb343f2ae36d7047276ba9eecda764cacc180e9f965136ebb5514": {
    "describe": {
      "columns": [
        {
          "name": "day_timestamp!",
          "ordinal": 0,
          "type_info": "Timestamptz"
        },
        {
          "name": "supply!",
          "ordinal": 1,
          "type_info": "Float8"
        }
      ],
      "nullable": [
        null,
        null
      ],
      "parameters": {
        "Left": [
          "Timestamptz"
        ]
      }
    },
    "query": "\n                SELECT\n                    DISTINCT ON (DATE_TRUNC('day', timestamp)) DATE_TRUNC('day', timestamp) AS \"day_timestamp!\",\n                    supply::FLOAT8 / 1e18 AS \"supply!\"\n                FROM\n                    eth_supply\n                WHERE\n                    timestamp >= $1\n                ORDER BY\n                    DATE_TRUNC('day', timestamp), timestamp ASC\n                "
  },
  "cf1180963d6c58dda37e2468b2919a37bbc799980be97478ba727f91f9cd4077": {
    "describe": {
      "columns": [
        {
          "name": "gwei!",
          "ordinal": 0,
          "type_info": "Int8"
        }
      ],
      "nullable": [
        false
      ],
      "parameters": {
        "Left": [
          "Timestamptz"
        ]
      }
    },
    "query": "\n            SELECT gwei AS \"gwei!\"\n            FROM beacon_issuance\n            WHERE timestamp >= $1\n            ORDER BY timestamp ASC\n            LIMIT 1\n             "
  },
  "d3bf0b8a5482556c44f37153e8e2dd3f95d96d3e0aa684d414586740c7369f2a": {
    "describe": {
      "columns": [
        {
          "name": "ethusd",
          "ordinal": 0,
          "type_info": "Float8"
        }
      ],
      "nullable": [
        false
      ],
      "parameters": {
        "Left": [
          "Timestamptz"
        ]
      }
    },
    "query": "\n            SELECT ethusd\n            FROM eth_prices\n            WHERE timestamp = $1\n            "
  },
  "d67dfd2fde9ed1d9dffcb31fd7a327fe7c42c43b1363401a8370b7c883a502ab": {
    "describe": {
      "columns": [
        {
          "name": "burn_sum_wei!",
          "ordinal": 0,
          "type_info": "Text"
        },
        {
          "name": "burn_sum_usd!",
          "ordinal": 1,
          "type_info": "Float8"
        }
      ],
      "nullable": [
        null,
        null
      ],
      "parameters": {
        "Left": [
          "Int4",
          "Int4"
        ]
      }
    },
    "query": "\n            SELECT\n                SUM(base_fee_per_gas::NUMERIC(78) * gas_used::NUMERIC(78))::TEXT\n                    AS \"burn_sum_wei!\",\n                SUM(base_fee_per_gas::NUMERIC(78) * gas_used::NUMERIC(78) / 1e18 * eth_price)\n                    AS \"burn_sum_usd!\"\n            FROM\n                blocks_next\n            WHERE\n                number >= $1 AND number <= $2\n            "
  },
  "d701446dc558dca2ce46c95c23a0683bbfcea6ebe25201968f7b59e15b484cc5": {
    "describe": {
      "columns": [
        {
          "name": "timestamp",
          "ordinal": 0,
          "type_info": "Timestamptz"
        }
      ],
      "nullable": [
        false
      ],
      "parameters": {
        "Left": [
          "Int4"
        ]
      }
    },
    "query": "\n            SELECT\n                timestamp\n            FROM\n                blocks_next\n            WHERE\n                number = $1\n            "
  },
  "d8bcd292eb9c526f02d2b1d71b1e551f9620403943400697940e01d3360958aa": {
    "describe": {
      "columns": [],
      "nullable": [],
      "parameters": {
        "Left": [
          "Int4"
        ]
      }
    },
    "query": "\n        DELETE FROM\n            eth_supply\n        WHERE\n            deposits_slot = $1\n            OR balances_slot = $1\n        "
  },
  "e629b9d9f49fb724cd7c02288f174d62ff4e87620277aff0248d88c15f90fe2d": {
    "describe": {
      "columns": [
        {
          "name": "exists!",
          "ordinal": 0,
          "type_info": "Bool"
        }
      ],
      "nullable": [
        null
      ],
      "parameters": {
        "Left": [
          "Text"
        ]
      }
    },
    "query": "\n            SELECT EXISTS (\n                SELECT 1\n                FROM blocks_next\n                WHERE hash = $1\n            ) AS \"exists!\"\n            "
  },
  "e81d51231c91dc84d5279e155932ec43cd1157cbcab70a0c9a82aff946c3e85f": {
    "describe": {
      "columns": [],
      "nullable": [],
      "parameters": {
        "Left": [
          "Int4"
        ]
      }
    },
    "query": "\n        DELETE FROM beacon_issuance\n        WHERE state_root IN (\n            SELECT state_root FROM beacon_states\n            WHERE slot >= $1\n        )\n        "
  },
  "ea004ca78abb79441aa0fb5ac65a2b1eb632476ce14df0333c73806451b0f656": {
    "describe": {
      "columns": [
        {
          "name": "number",
          "ordinal": 0,
          "type_info": "Int4"
        },
        {
          "name": "base_fee_per_gas!",
          "ordinal": 1,
          "type_info": "Int8"
        }
      ],
      "nullable": [
        false,
        false
      ],
      "parameters": {
        "Left": [
          "Interval"
        ]
      }
    },
    "query": "\n            SELECT\n                number,\n                base_fee_per_gas AS \"base_fee_per_gas!\"\n            FROM\n                blocks_next\n            WHERE\n                timestamp >= NOW() - $1::INTERVAL\n            ORDER BY base_fee_per_gas DESC\n            LIMIT 1\n            "
  },
  "ed26cd65f0605acd6eb54c5804008c84b11f26c952a35ee6eb6d5c92dac55efa": {
    "describe": {
      "columns": [
        {
          "name": "slot",
          "ordinal": 0,
          "type_info": "Int4"
        },
        {
          "name": "supply!",
          "ordinal": 1,
          "type_info": "Float8"
        },
        {
          "name": "timestamp",
          "ordinal": 2,
          "type_info": "Timestamptz"
        }
      ],
      "nullable": [
        false,
        null,
        false
      ],
      "parameters": {
        "Left": []
      }
    },
    "query": "\n        WITH numbered_rows AS (\n            SELECT\n                ROW_NUMBER() OVER (ORDER BY timestamp) AS row_number,\n                balances_slot AS slot,\n                supply::FLOAT8 / 1e18 AS supply,\n                timestamp\n            FROM eth_supply\n        )\n        SELECT \n          slot,\n          supply AS \"supply!\",\n          timestamp\n        FROM numbered_rows\n        WHERE row_number % 32000 = 1\n        "
  },
  "f2d4faaff81c4ee97a6c7a092754714db1f274e232614fcd628713f8f2d31bc3": {
    "describe": {
      "columns": [
        {
          "name": "base_fee_per_gas",
          "ordinal": 0,
          "type_info": "Int8"
        },
        {
          "name": "difficulty",
          "ordinal": 1,
          "type_info": "Int8"
        },
        {
          "name": "eth_price",
          "ordinal": 2,
          "type_info": "Float8"
        },
        {
          "name": "gas_used",
          "ordinal": 3,
          "type_info": "Int4"
        },
        {
          "name": "hash",
          "ordinal": 4,
          "type_info": "Text"
        },
        {
          "name": "number",
          "ordinal": 5,
          "type_info": "Int4"
        },
        {
          "name": "parent_hash",
          "ordinal": 6,
          "type_info": "Text"
        },
        {
          "name": "timestamp",
          "ordinal": 7,
          "type_info": "Timestamptz"
        },
        {
          "name": "total_difficulty!",
          "ordinal": 8,
          "type_info": "Text"
        }
      ],
      "nullable": [
        false,
        false,
        false,
        false,
        false,
        false,
        false,
        false,
        null
      ],
      "parameters": {
        "Left": []
      }
    },
    "query": "\n            SELECT\n                base_fee_per_gas,\n                difficulty,\n                eth_price,\n                gas_used,\n                hash,\n                number,\n                parent_hash,\n                timestamp,\n                total_difficulty::TEXT AS \"total_difficulty!\"\n            FROM\n                blocks_next\n            ORDER BY\n                number DESC\n            LIMIT 1\n            "
  },
  "fb8a334d72f27895aca5a22d08edcbfe971a4739d4922eda48098e8e641040a4": {
    "describe": {
      "columns": [
        {
          "name": "average!",
          "ordinal": 0,
          "type_info": "Float8"
        }
      ],
      "nullable": [
        null
      ],
      "parameters": {
        "Left": []
      }
    },
    "query": "\n        SELECT\n            AVG(ethusd) AS \"average!\"\n        FROM\n            eth_prices\n        WHERE timestamp >= NOW() - '24 hours'::INTERVAL\n        "
  }
}